MercatorConverter/__init__.py
MercatorConverter/conversion.py
mercatorconverter-0.0.2.dist-info/METADATA
mercatorconverter-0.0.2.dist-info/WHEEL
mercatorconverter-0.0.2.dist-info/licenses/LICENSE
mercatorconverter-0.0.2.dist-info/RECORD
