Metadata-Version: 2.3
Name: MercatorConverter
Version: 0.0.2
Summary: Mercator Coordinate Converter is a Python package designed to simplify the conversion of geographical projection coordinates, such as latitude and longitude, into Mercator coordinates, and vice versa.
Project-URL: Homepage, https://github.com/donilpro/MercatorConverter
Project-URL: Issues, https://github.com/donilpro/MercatorConverter/issues
Author-email: Daniil Malygin <donil858@gmail.com>
License-File: LICENSE
Classifier: License :: OSI Approved :: MIT License
Classifier: Operating System :: OS Independent
Classifier: Programming Language :: Python :: 3
Requires-Python: >=3.8
